aiohuesyncbox/__init__.py
aiohuesyncbox/behavior.py
aiohuesyncbox/device.py
aiohuesyncbox/errors.py
aiohuesyncbox/execution.py
aiohuesyncbox/hdmi.py
aiohuesyncbox/helpers.py
aiohuesyncbox/hsb_cacert.py
aiohuesyncbox/hue.py
aiohuesyncbox/huesyncbox.py
aiohuesyncbox/py.typed
aiohuesyncbox-0.0.31.dist-info/licenses/LICENSE
aiohuesyncbox-0.0.31.dist-info/METADATA
aiohuesyncbox-0.0.31.dist-info/WHEEL
aiohuesyncbox-0.0.31.dist-info/top_level.txt
aiohuesyncbox-0.0.31.dist-info/RECORD
