Metadata-Version: 2.4
Name: aiohuesyncbox
Version: 0.0.31
Summary: Asyncio package to communicate with a Philips Hue Play HDMI Sync Box.
Author-email: Michel van de Wetering <michel.van.de.wetering@gmail.com>
License: Apache-2.0
Project-URL: Homepage, https://github.com/mvdwetering/aiohuesyncbox
Classifier: Programming Language :: Python :: 3
Classifier: License :: OSI Approved :: Apache Software License
Classifier: Operating System :: OS Independent
Classifier: Development Status :: 5 - Production/Stable
Classifier: Intended Audience :: Developers
Classifier: Topic :: Home Automation
Classifier: Topic :: Software Development :: Libraries
Requires-Python: >=3.8
License-File: LICENSE
Requires-Dist: aiohttp>=3.9.0
Provides-Extra: test
Requires-Dist: mypy==1.11.0; extra == "test"
Requires-Dist: ruff==0.5.5; extra == "test"
Dynamic: license-file
